sofirpy/__init__.py
sofirpy/common.py
sofirpy/py.typed
sofirpy/utils.py
sofirpy/fmu_export/__init__.py
sofirpy/fmu_export/dymola_fmu_export.py
sofirpy/fmu_export/fmu_export.py
sofirpy/fmu_export/open_modelica_fmu_export.py
sofirpy/rdm/__init__.py
sofirpy/rdm/run.py
sofirpy/rdm/hdf5/__init__.py
sofirpy/rdm/hdf5/config.py
sofirpy/rdm/hdf5/deserialize.py
sofirpy/rdm/hdf5/hdf5.py
sofirpy/rdm/hdf5/hdf5_to_run.py
sofirpy/rdm/hdf5/run_to_hdf5.py
sofirpy/rdm/hdf5/serialize.py
sofirpy/simulation/__init__.py
sofirpy/simulation/fmu.py
sofirpy/simulation/plot.py
sofirpy/simulation/simulation.py
sofirpy/simulation/simulation_entity.py
sofirpy-1.0.2.dist-info/LICENSE
sofirpy-1.0.2.dist-info/METADATA
sofirpy-1.0.2.dist-info/WHEEL
sofirpy-1.0.2.dist-info/top_level.txt
sofirpy-1.0.2.dist-info/RECORD
