Metadata-Version: 2.1
Name: sofirpy
Version: 1.0.2
Summary: Framework for simulating FMUs and custom models written in python.
Author-email: Daniele Inturri <daniele.inturri@stud.tu-darmstadt.de>
License: MIT License
Project-URL: repository, https://git.rwth-aachen.de/sofirpy/sofirpy
Project-URL: documentation, https://sofirpy.readthedocs.io/
Keywords: simulation,fmu
Classifier: License :: OSI Approved :: MIT License
Classifier: Programming Language :: Python :: 3
Classifier: Programming Language :: Python :: 3.9
Classifier: Programming Language :: Python :: 3.10
Classifier: Programming Language :: Python :: 3 :: Only
Requires-Python: >=3.9
License-File: LICENSE
Requires-Dist: FMPy >=0.3.0
Requires-Dist: cloudpickle >=2.2.1
Requires-Dist: tqdm >=4.60.0
Requires-Dist: h5py >=3.0.0
Requires-Dist: matplotlib >=3.2.0
Requires-Dist: numpy >=1.20.0
Requires-Dist: pandas >=1.3.0
Requires-Dist: OMpython >=3.4.0
Requires-Dist: typing-extensions >=4.3.0
Requires-Dist: pydantic >=2.0.0
Provides-Extra: dev
Requires-Dist: black >=22.12.0 ; extra == 'dev'
Requires-Dist: isort >=5.12.0 ; extra == 'dev'
Requires-Dist: pylint >=2.15.3 ; extra == 'dev'
Requires-Dist: pre-commit >=3.2.2 ; extra == 'dev'
Requires-Dist: ruff >=0.1.11 ; extra == 'dev'
Provides-Extra: doc
Requires-Dist: sphinx >=5.1.1 ; extra == 'doc'
Requires-Dist: sphinx-rtd-theme >=1.0.0 ; extra == 'doc'
Provides-Extra: test
Requires-Dist: pytest >=7.1.2 ; extra == 'test'
Requires-Dist: pytest-cov >=3.0.0 ; extra == 'test'
Requires-Dist: mypy >=1.5.1 ; extra == 'test'
Requires-Dist: pandas-stubs >=1.4.3.220822 ; extra == 'test'
Requires-Dist: syrupy >=4.5.0 ; extra == 'test'
Requires-Dist: types-setuptools >=68.2.0.0 ; extra == 'test'
Requires-Dist: types-tqdm >=4.64.5 ; extra == 'test'
Requires-Dist: types-pytz >=2022.2.1.0 ; extra == 'test'
